xmlstore/__init__.py
xmlstore/converter-1.0.xsd
xmlstore/datatypes.py
xmlstore/gui_qt4.py
xmlstore/qt_compat.py
xmlstore/util.py
xmlstore/versioning.py
xmlstore/xmlstore-1.0.xsd
xmlstore/xmlstore-base-1.0.xsd
xmlstore/xmlstore.py
xmlstore-0.9.16.dist-info/METADATA
xmlstore-0.9.16.dist-info/WHEEL
xmlstore-0.9.16.dist-info/licenses/LICENSE
xmlstore-0.9.16.dist-info/RECORD
